modoo/__init__.py
modoo/adddocmeta.py
modoo/checkwd.py
modoo/cli.py
modoo/convid.py
modoo/fixid.py
modoo/idfuncs.py
modoo/mapid.py
modoo/mergeza.py
modoo/validate.py
modoo/zafuncs.py
modoo-0.1.4.dist-info/entry_points.txt
modoo-0.1.4.dist-info/WHEEL
modoo-0.1.4.dist-info/METADATA
modoo-0.1.4.dist-info/RECORD
